{"lastUsed":1611352782579,"path":"C:\/Users\/Leo\/Documents\/Ciências da Computação\/Worksapce JAVA\/GAME\/JAVAJOGO","projectCount":1,"recentFiles":[{"path":"\/Jogo\/src\/Jogo2D","parentWorkspace":"C:\/Users\/Leo\/Documents\/Ciências da Computação\/Worksapce JAVA\/GAME\/JAVAJOGO","name":"RodolfoHeroi.java"},{"path":"\/Jogo\/src","parentWorkspace":"C:\/Users\/Leo\/Documents\/Ciências da Computação\/Worksapce JAVA\/GAME\/JAVAJOGO","name":"2.jpeg"},{"path":"\/Jogo\/src","parentWorkspace":"C:\/Users\/Leo\/Documents\/Ciências da Computação\/Worksapce JAVA\/GAME\/JAVAJOGO","name":"WhatsApp Image 2018-11-06 at 12.46.03.jpeg"},{"path":"\/Jogo\/src","parentWorkspace":"C:\/Users\/Leo\/Documents\/Ciências da Computação\/Worksapce JAVA\/GAME\/JAVAJOGO","name":"WhatsApp Image 2018-11-06 at 12.46.03 (1).jpeg"},{"path":"\/Jogo\/src","parentWorkspace":"C:\/Users\/Leo\/Documents\/Ciências da Computação\/Worksapce JAVA\/GAME\/JAVAJOGO","name":"WhatsApp Image 2018-11-06 at 12.46.02.jpeg"},{"path":"\/Jogo\/src","parentWorkspace":"C:\/Users\/Leo\/Documents\/Ciências da Computação\/Worksapce JAVA\/GAME\/JAVAJOGO","name":"WhatsApp Image 2018-11-06 at 12.46.02 (2).jpeg"},{"path":"\/Jogo\/src","parentWorkspace":"C:\/Users\/Leo\/Documents\/Ciências da Computação\/Worksapce JAVA\/GAME\/JAVAJOGO","name":"WhatsApp Image 2018-11-06 at 12.46.02 (1).jpeg"},{"path":"\/Jogo\/src","parentWorkspace":"C:\/Users\/Leo\/Documents\/Ciências da Computação\/Worksapce JAVA\/GAME\/JAVAJOGO","name":"WhatsApp Image 2018-11-06 at 12.46.01.jpeg"},{"path":"\/Jogo\/src\/Jogo2D","parentWorkspace":"C:\/Users\/Leo\/Documents\/Ciências da Computação\/Worksapce JAVA\/GAME\/JAVAJOGO","name":"Main.java"},{"path":"\/Jogo\/src\/Jogo2D","parentWorkspace":"C:\/Users\/Leo\/Documents\/Ciências da Computação\/Worksapce JAVA\/GAME\/JAVAJOGO","name":"MonstroOrc.java"},{"path":"\/Jogo\/src\/Jogo2D","parentWorkspace":"C:\/Users\/Leo\/Documents\/Ciências da Computação\/Worksapce JAVA\/GAME\/JAVAJOGO","name":"MostroDemonio.java"},{"path":"\/Jogo\/src\/Jogo2D","parentWorkspace":"C:\/Users\/Leo\/Documents\/Ciências da Computação\/Worksapce JAVA\/GAME\/JAVAJOGO","name":"Jogo.java"},{"path":"\/Jogo\/src\/Jogo2D","parentWorkspace":"C:\/Users\/Leo\/Documents\/Ciências da Computação\/Worksapce JAVA\/GAME\/JAVAJOGO","name":"Cenario.java"},{"path":"\/Jogo\/src\/Jogo2D","parentWorkspace":"C:\/Users\/Leo\/Documents\/Ciências da Computação\/Worksapce JAVA\/GAME\/JAVAJOGO","name":"MostroZumbi.java"},{"path":"\/Jogo\/src\/Jogo2D","parentWorkspace":"C:\/Users\/Leo\/Documents\/Ciências da Computação\/Worksapce JAVA\/GAME\/JAVAJOGO","name":"Hit.java"}]}